email_verification/__init__.py
email_verification/emailverf.py
email_verification/exceptions.py
emailverf-0.1.dist-info/LICENSE.txt
emailverf-0.1.dist-info/METADATA
emailverf-0.1.dist-info/WHEEL
emailverf-0.1.dist-info/top_level.txt
emailverf-0.1.dist-info/RECORD
